fastapi_frame/__init__.py
fastapi_frame/fastapi/__init__.py
fastapi_frame/fastapi/__main__.py
fastapi_frame/fastapi/_compat.py
fastapi_frame/fastapi/applications.py
fastapi_frame/fastapi/background.py
fastapi_frame/fastapi/cli.py
fastapi_frame/fastapi/concurrency.py
fastapi_frame/fastapi/custom_types.py
fastapi_frame/fastapi/datastructures.py
fastapi_frame/fastapi/encoders.py
fastapi_frame/fastapi/exception_handlers.py
fastapi_frame/fastapi/exceptions.py
fastapi_frame/fastapi/fastapi_requests.py
fastapi_frame/fastapi/logger.py
fastapi_frame/fastapi/param_functions.py
fastapi_frame/fastapi/params.py
fastapi_frame/fastapi/py.typed
fastapi_frame/fastapi/responses.py
fastapi_frame/fastapi/routing.py
fastapi_frame/fastapi/staticfiles.py
fastapi_frame/fastapi/templating.py
fastapi_frame/fastapi/testclient.py
fastapi_frame/fastapi/utils.py
fastapi_frame/fastapi/websockets.py
fastapi_frame/fastapi/dependencies/__init__.py
fastapi_frame/fastapi/dependencies/registry.py
fastapi_frame/fastapi/dependencies/entities/__init__.py
fastapi_frame/fastapi/dependencies/entities/endpoint.py
fastapi_frame/fastapi/dependencies/entities/framework.py
fastapi_frame/fastapi/middleware/__init__.py
fastapi_frame/fastapi/middleware/cors.py
fastapi_frame/fastapi/middleware/gzip.py
fastapi_frame/fastapi/middleware/httpsredirect.py
fastapi_frame/fastapi/middleware/trustedhost.py
fastapi_frame/fastapi/middleware/wsgi.py
fastapi_frame/fastapi/openapi/__init__.py
fastapi_frame/fastapi/openapi/base.py
fastapi_frame/fastapi/openapi/main_controller.py
fastapi_frame/fastapi/security/__init__.py
fastapi_frame/fastapi/security/api_key.py
fastapi_frame/fastapi/security/base.py
fastapi_frame/fastapi/security/http.py
fastapi_frame/fastapi/security/oauth2.py
fastapi_frame/fastapi/security/open_id_connect_url.py
fastapi_frame/fastapi/security/utils.py
fastapi_frame-0.1.4.dist-info/METADATA
fastapi_frame-0.1.4.dist-info/WHEEL
fastapi_frame-0.1.4.dist-info/licenses/LICENSE
fastapi_frame-0.1.4.dist-info/RECORD
