Metadata-Version: 2.4
Name: fastapi-frame
Version: 0.1.4
Summary: FastAPI framework template structure without dependencies - use as a starting point for FastAPI projects
Project-URL: Homepage, https://github.com/jordi/fastapi-frame
Project-URL: Documentation, https://github.com/jordi/fastapi-frame#readme
Project-URL: Repository, https://github.com/jordi/fastapi-frame.git
Project-URL: Bug Tracker, https://github.com/jordi/fastapi-frame/issues
Author-email: Jordi <jordi@example.com>
Maintainer-email: Jordi <jordi@example.com>
License-Expression: MIT
License-File: LICENSE
Keywords: api,async,fastapi,framework,openapi,templates,web
Classifier: Development Status :: 4 - Beta
Classifier: Framework :: FastAPI
Classifier: Intended Audience :: Developers
Classifier: License :: OSI Approved :: MIT License
Classifier: Operating System :: OS Independent
Classifier: Programming Language :: Python :: 3
Classifier: Programming Language :: Python :: 3.8
Classifier: Programming Language :: Python :: 3.9
Classifier: Programming Language :: Python :: 3.10
Classifier: Programming Language :: Python :: 3.11
Classifier: Programming Language :: Python :: 3.12
Classifier: Topic :: Internet :: WWW/HTTP :: HTTP Servers
Classifier: Topic :: Software Development :: Libraries :: Application Frameworks
Classifier: Topic :: Software Development :: Libraries :: Python Modules
Requires-Python: >=3.8
Provides-Extra: all
Requires-Dist: black>=23.0.0; extra == 'all'
Requires-Dist: isort>=5.12.0; extra == 'all'
Provides-Extra: dev
Requires-Dist: black>=23.0.0; extra == 'dev'
Requires-Dist: isort>=5.12.0; extra == 'dev'
